chartmogul_mcp/api_client.py
chartmogul_mcp/mcp_server.py
chartmogul_mcp/utils.py
chartmogul_mcp_server-0.3.1.dist-info/licenses/LICENSE
chartmogul_mcp_server-0.3.1.dist-info/METADATA
chartmogul_mcp_server-0.3.1.dist-info/WHEEL
chartmogul_mcp_server-0.3.1.dist-info/top_level.txt
chartmogul_mcp_server-0.3.1.dist-info/RECORD
