Metadata-Version: 2.4
Name: chartmogul-mcp-server
Version: 0.3.1
Summary: ChartMogul's MCP server
Project-URL: Home, https://github.com/chartmogul/chartmogul-mcp-server
Requires-Python: >=3.13
License-File: LICENSE
Requires-Dist: chartmogul>=4.6.1
Requires-Dist: mcp[cli]>=1.7.1
Requires-Dist: python-dotenv>=1.1.0
Dynamic: license-file
